CHANGES
MANIFEST.in
README
setup.py
Schema_Object.egg-info/PKG-INFO
Schema_Object.egg-info/SOURCES.txt
Schema_Object.egg-info/dependency_links.txt
Schema_Object.egg-info/requires.txt
Schema_Object.egg-info/top_level.txt
schema_object.egg-info/PKG-INFO
schema_object.egg-info/SOURCES.txt
schema_object.egg-info/dependency_links.txt
schema_object.egg-info/requires.txt
schema_object.egg-info/top_level.txt
schemaobject/__init__.py
schemaobject/collections.py
schemaobject/column.py
schemaobject/connection.py
schemaobject/database.py
schemaobject/foreignkey.py
schemaobject/index.py
schemaobject/option.py
schemaobject/procedure.py
schemaobject/schema.py
schemaobject/table.py
schemaobject/trigger.py
schemaobject/view.py